image_knocker/__init__.py
image_knocker/image_knock.py
image_knocker/image_knocker.py
image_knocker-0.0.1.4.dist-info/LICENSE
image_knocker-0.0.1.4.dist-info/METADATA
image_knocker-0.0.1.4.dist-info/WHEEL
image_knocker-0.0.1.4.dist-info/entry_points.txt
image_knocker-0.0.1.4.dist-info/top_level.txt
image_knocker-0.0.1.4.dist-info/RECORD
