Metadata-Version: 2.1
Name: image-knocker
Version: 0.0.1.4
Summary: Knock your images before these make you painful
Home-page: https://github.com/developer0hye/image-knocker
Author: Yonghye Kwon
Author-email: developer.0hye@gmail.com
License: Apache
Keywords: image,img
Platform: UNKNOWN
Classifier: Programming Language :: Python :: 3
Classifier: License :: OSI Approved :: MIT License
Classifier: Operating System :: OS Independent
Requires-Python: >=3.6
License-File: LICENSE
Requires-Dist: pillow
Requires-Dist: tqdm
